{
  "type": "object",
  "required": ["style", "editable", "graphTooltip", "schemaVersion"],
  "properties": {
    "id": {
      "description": "Unique numeric identifier for the dashboard.\nTODO must isolate or remove identifiers local to a Grafana instance...?",
      "type": "number"
    },
    "uid": {
      "description": "Unique dashboard identifier that can be generated by anyone. string (8-40)",
      "type": "string"
    },
    "title": {
      "description": "Title of dashboard.",
      "type": "string"
    },
    "description": {
      "description": "Description of dashboard.",
      "type": "string"
    },
    "gnetId": {
      "type": "string"
    },
    "tags": {
      "description": "Tags associated with dashboard.",
      "type": "array",
      "items": {
        "type": "string"
      }
    },
    "style": {
      "description": "Theme of dashboard.",
      "type": "string",
      "enum": ["light", "dark"],
      "default": "light"
    },
    "timezone": {
      "description": "Timezone of dashboard,",
      "type": "string",
      "enum": ["browser", "utc"],
      "default": "browser"
    },
    "editable": {
      "description": "Whether a dashboard is editable or not.",
      "type": "boolean",
      "default": true
    },
    "graphTooltip": {
      "description": "0 for no shared crosshair or tooltip (default).\n1 for shared crosshair.\n2 for shared crosshair AND shared tooltip.",
      "type": "number",
      "minimum": 0,
      "maximum": 2,
      "default": 0
    },
    "time": {
      "description": "Time range for dashboard, e.g. last 6 hours, last 7 days, etc",
      "type": "object",
      "required": ["from", "to"],
      "properties": {
        "from": {
          "type": "string",
          "default": "now-6h"
        },
        "to": {
          "type": "string",
          "default": "now"
        }
      }
    },
    "timepicker": {
      "description": "Timepicker metadata.",
      "type": "object",
      "required": ["collapse", "enable", "hidden", "refresh_intervals"],
      "properties": {
        "collapse": {
          "description": "Whether timepicker is collapsed or not.",
          "type": "boolean",
          "default": false
        },
        "enable": {
          "description": "Whether timepicker is enabled or not.",
          "type": "boolean",
          "default": true
        },
        "hidden": {
          "description": "Whether timepicker is visible or not.",
          "type": "boolean",
          "default": false
        },
        "refresh_intervals": {
          "description": "Selectable intervals for auto-refresh.",
          "type": "array",
          "items": {
            "type": "string"
          },
          "default": ["5s", "10s", "30s", "1m", "5m", "15m", "30m", "1h", "2h", "1d"]
        }
      }
    },
    "templating": {
      "type": "object",
      "required": ["list"],
      "properties": {
        "list": {
          "description": "Templating.",
          "type": "array",
          "items": {
            "type": "object"
          }
        }
      }
    },
    "annotations": {
      "type": "object",
      "required": ["list"],
      "properties": {
        "list": {
          "description": "Annotations.",
          "type": "array",
          "items": {
            "type": "object",
            "required": ["builtIn", "datasource", "type", "showIn"],
            "properties": {
              "builtIn": {
                "type": "number",
                "default": 0
              },
              "datasource": {
                "description": "Datasource to use for annotation.",
                "type": "string"
              },
              "enable": {
                "description": "Whether annotation is enabled.",
                "type": "boolean",
                "default": true
              },
              "hide": {
                "description": "Whether to hide annotation.",
                "type": "boolean",
                "default": false
              },
              "iconColor": {
                "description": "Annotation icon color.",
                "type": "string"
              },
              "name": {
                "description": "Name of annotation.",
                "type": "string"
              },
              "type": {
                "type": "string",
                "default": "dashboard"
              },
              "rawQuery": {
                "description": "Query for annotation data.",
                "type": "string"
              },
              "showIn": {
                "type": "number",
                "default": 0
              }
            }
          }
        }
      }
    },
    "refresh": {
      "description": "Auto-refresh interval.",
      "type": "string"
    },
    "schemaVersion": {
      "description": "Version of the JSON schema, incremented each time a Grafana update brings\nchanges to said schema.",
      "type": "number",
      "default": 25
    },
    "version": {
      "description": "Version of the dashboard, incremented each time the dashboard is updated.",
      "type": "number"
    },
    "panels": {
      "type": "array"
    }
  }
}
