{
  "title": "Welcome to Grafana!",
  "time": {
    "from": "now-6h",
    "to": "now"
  },
  "templating": {
    "list": []
  },
  "rows": [
    {
      "title": "Welcome to Grafana",
      "height": "150px",
      "editable": true,
      "collapse": false,
      "panels": [
        {
          "error": false,
          "span": 12,
          "editable": true,
          "type": "text",
          "loadingEditor": false,
          "mode": "markdown",
          "content": "####Thank you for trying out Grafana! \n\nGeneral documentation is found in the readme and in the wiki section of the [Github Project](https://github.com/torkelo/grafana). If you encounter any problem or have an idea for an improvement do not hesitate to open a github issue. \n\nTips: \n\n- Ctrl+S saves the current dashboard\n- Ctrl+F Opens the dashboard finder (searches elastic search)\n- Ctrl+H Hide/show row controls \n- Click and drag graph title to move panel (only works when row controls are enabled)\n\nIf you do not see a graph in the panel below, the browser cannot access your graphite installation. Please make sure that datasources property in config.js is correctly set and that any urls accessible from your browser.",
          "style": {},
          "title": "Welcome to Grafana"
        }
      ]
    },
    {
      "title": "test",
      "height": "250px",
      "editable": true,
      "collapse": false,
      "panels": [
        {
          "span": 12,
          "editable": true,
          "type": "graph",
          "x-axis": true,
          "y-axis": true,
          "scale": 1,
          "y_formats": ["short", "short"],
          "grid": {
            "max": null,
            "min": null
          },
          "logBase" : false,
          "resolution": 100,
          "lines": true,
          "fill": 1,
          "linewidth": 2,
          "points": false,
          "pointradius": 5,
          "bars": false,
          "stack": true,
          "spyable": true,
          "options": false,
          "legend": true,
          "interactive": true,
          "legend_counts": true,
          "timezone": "browser",
          "percentage": false,
          "zerofill": true,
          "nullPointMode": "connected",
          "steppedLine": false,
          "tooltip": {
            "value_type": "cumulative"
          },
          "targets": [
            {
                "target" : "offset(absolute(randomWalk('1000')),1000)"
            },
            {
                "target" : "offset(absolute(randomWalk('100')),100)"
            },
            {
              "target" : "offset(absolute(randomWalk('10')),10)"
            }


            ],
          "aliasColors": {},
          "aliasYAxis": {},
          "title": "Graphite test"
        }
      ]
    }
  ],
  "editable": true,
  "failover": false,
  "style": "dark",
  "pulldowns": [
    {
      "type": "filtering",
      "collapse": false,
      "notice": false,
      "enable": false
    }
  ],
  "nav": [
    {
      "type": "timepicker",
      "collapse": false,
      "notice": false,
      "enable": true,
      "status": "Stable",
      "time_options": [
        "5m",
        "15m",
        "1h",
        "6h",
        "12h",
        "24h",
        "2d",
        "7d",
        "30d"
      ],
      "refresh_intervals": [
        "5s",
        "10s",
        "30s",
        "1m",
        "5m",
        "15m",
        "30m",
        "1h",
        "2h",
        "1d"
      ],
      "now": true
    }
  ],
  "refresh": false
}
